nrkdl/__init__.py
nrkdl/nrkdl.py
nrkdl-1.2.2.dist-info/METADATA
nrkdl-1.2.2.dist-info/WHEEL
nrkdl-1.2.2.dist-info/entry_points.txt
nrkdl-1.2.2.dist-info/top_level.txt
nrkdl-1.2.2.dist-info/RECORD
