Metadata-Version: 2.1
Name: nrkdl
Version: 1.2.2
Summary: Download movies/tv-shows from nrk.no
Author: jenlys
Project-URL: Source, https://github.com/jenslys/nrkdl/
Project-URL: Tracker, https://github.com/jenslys/nrkdl/issues
Classifier: Programming Language :: Python :: 3
Classifier: License :: OSI Approved :: MIT License
Classifier: Operating System :: OS Independent
Requires-Python: >=3.6
Requires-Dist: yt-dlp
Requires-Dist: requests
